netmiko_balabit/__init__.py
netmiko_balabit/balabit_scb_ssh.py
netmiko_balabit-0.1.2.dist-info/LICENSE
netmiko_balabit-0.1.2.dist-info/METADATA
netmiko_balabit-0.1.2.dist-info/WHEEL
netmiko_balabit-0.1.2.dist-info/top_level.txt
netmiko_balabit-0.1.2.dist-info/RECORD
