Metadata-Version: 2.1
Name: netmiko-balabit
Version: 0.1.2
Summary: Out of tree netmiko driver for balabit scb
Home-page: https://github.com/jinjamator/netmiko_balabit
Author: Wilhelm Putz
Author-email: wp@aci.guru
License: ASL V2
Platform: UNKNOWN
Classifier: License :: OSI Approved :: Apache Software License
Classifier: Programming Language :: Python :: 3.7
Classifier: Programming Language :: Python :: 3.8
Classifier: Topic :: System :: Installation/Setup
Classifier: Topic :: System :: Systems Administration
Classifier: Topic :: Utilities
Requires-Python: >=3.7
License-File: LICENSE
Requires-Dist: netmiko (>=4.1.2)
